{"stats":{"minecraft:killed_by":{"minecraft:player":17},"minecraft:dropped":{"refurbished_furniture:cheese":1,"cbb:david":2,"minecraft:birch_slab":3,"minecraft:deepslate_tile_stairs":1,"waystones:sharestone":1,"minecraft:crimson_roots":1,"refurbished_furniture:glow_berry_jam":1,"minecraft:writable_book":1,"minecraft:gold_ingot":51,"refurbished_furniture:sea_salt":1,"minecraft:blackstone":1,"minecraft:ancient_debris":2,"minecraft:obsidian":1,"farmersdelight:cabbage":7,"minecraft:tipped_arrow":1,"minecraft:deepslate_tiles":1,"minecraft:melon_seeds":3,"music:millpp":1,"minecraft:crying_obsidian":1,"refurbished_furniture:workbench":1,"minecraft:written_book":1,"minecraft:wheat_seeds":2,"minecraft:book":3,"minecraft:deepslate_tile_slab":1,"minecraft:oxeye_daisy":1,"minecraft:nether_gold_ore":1,"minecraft:wooden_hoe":26,"farmersdelight:cabbage_seeds":22,"refurbished_furniture:oak_cutting_board":1,"minecraft:flint_and_steel":1,"refurbished_furniture:sweet_berry_jam_toast":1},"minecraft:custom":{"minecraft:interact_with_crafting_table":16,"minecraft:open_barrel":21,"minecraft:leave_game":10,"minecraft:time_since_death":2080,"minecraft:damage_resisted":115,"minecraft:sprint_one_cm":494818,"minecraft:damage_blocked_by_shield":1236,"minecraft:drop":140,"minecraft:play_time":385393,"minecraft:deaths":25,"minecraft:jump":3200,"minecraft:interact_with_brewingstand":2,"minecraft:walk_on_water_one_cm":17225,"minecraft:enchant_item":2,"minecraft:interact_with_furnace":15,"minecraft:play_record":14,"minecraft:interact_with_cartography_table":3,"minecraft:interact_with_loom":1,"minecraft:sleep_in_bed":7,"minecraft:waystone_activated":3,"minecraft:damage_dealt":3444,"minecraft:crouch_one_cm":19396,"minecraft:interact_with_smoker":4,"minecraft:interact_with_smithing_table":18,"minecraft:inspect_dropper":27,"minecraft:mob_kills":18,"minecraft:interact_with_anvil":12,"minecraft:climb_one_cm":2982,"minecraft:walk_one_cm":1249273,"minecraft:sneak_time":11563,"minecraft:walk_under_water_one_cm":5235,"minecraft:interact_with_lectern":2,"minecraft:interact_with_blast_furnace":7,"minecraft:total_world_time":385393,"minecraft:interact_with_grindstone":3,"minecraft:interact_with_stonecutter":2,"minecraft:time_since_rest":49,"minecraft:damage_taken":13427,"minecraft:swim_one_cm":11112,"minecraft:fly_one_cm":2135263,"minecraft:open_chest":89,"minecraft:fall_one_cm":79589},"minecraft:killed":{"minecraft:chicken":1,"minecraft:pig":3,"minecraft:salmon":3,"minecraft:sheep":2,"minecraft:cow":1,"minecraft:panda":6},"minecraft:crafted":{"minecraft:diamond_helmet":1,"minecraft:diamond_leggings":1,"minecraft:iron_boots":1,"minecraft:netherite_boots":2,"minecraft:melon_seeds":46,"minecraft:chest":2,"minecraft:netherite_helmet":2,"minecraft:birch_door":3,"farmersdelight:tomato_seeds":1,"minecraft:crafting_table":1,"minecraft:wooden_pickaxe":1,"minecraft:iron_helmet":1,"minecraft:birch_planks":240,"minecraft:iron_chestplate":1,"minecraft:stick":12,"minecraft:iron_ingot":36,"minecraft:stone_sword":1,"minecraft:gold_ingot":127,"minecraft:netherite_ingot":9,"minecraft:wooden_sword":1,"minecraft:stone_shovel":1,"minecraft:netherite_sword":1,"minecraft:netherite_chestplate":2,"minecraft:netherite_leggings":2,"minecraft:stone_pickaxe":1,"minecraft:diamond_boots":1,"minecraft:netherite_scrap":2,"minecraft:netherite_pickaxe":1,"minecraft:stone_axe":1,"minecraft:air":0,"minecraft:wooden_axe":1,"minecraft:iron_leggings":1,"minecraft:diamond_chestplate":1},"minecraft:mined":{"minecraft:farmland":2,"minecraft:grass_block":96,"minecraft:cracked_polished_blackstone_bricks":2,"minecraft:oxeye_daisy":1,"minecraft:gilded_blackstone":5,"minecraft:spawner":1,"coffee_delight:coffee_bush":2,"minecraft:polished_blackstone_bricks":9,"refurbished_furniture:red_cooler":1,"refurbished_furniture:oak_storage_cabinet":1,"minecraft:iron_ore":18,"minecraft:enchanting_table":1,"refurbished_furniture:light_toaster":1,"refurbished_furniture:oak_light_ceiling_fan":2,"farmersdelight:rice_panicles":150,"refurbished_furniture:light_ceiling_light":3,"minecraft:red_bed":2,"minecraft:blackstone":32,"minecraft:powder_snow":1,"minecraft:melon":25,"minecraft:chest":3,"refurbished_furniture:light_microwave":1,"refurbished_furniture:oak_cutting_board":3,"farmersdelight:cabbages":154,"minecraft:glass":2,"minecraft:cobblestone":2,"refurbished_furniture:yellow_lamp":1,"minecraft:sugar_cane":82,"minecraft:oak_planks":5,"minecraft:birch_sapling":3,"refurbished_furniture:computer":2,"minecraft:birch_log":7,"minecraft:wheat":181,"minecraft:birch_trapdoor":1,"minecraft:jukebox":1,"refurbished_furniture:light_electricity_generator":1,"minecraft:grass":14,"minecraft:beetroots":47,"minecraft:dirt":75,"refurbished_furniture:light_lightswitch":5,"farmersdelight:onions":72,"refurbished_furniture:doorbell":1,"minecraft:carrots":72,"minecraft:gold_block":16,"refurbished_furniture:red_grill":1,"refurbished_furniture:television":3,"minecraft:bookshelf":1,"minecraft:potatoes":42,"minecraft:stone":248,"refurbished_furniture:oak_storage_jar":1,"minecraft:basalt":7,"refurbished_furniture:light_fridge":1,"minecraft:dandelion":1,"minecraft:crafting_table":2,"minecraft:cornflower":1,"minecraft:tall_grass":2,"minecraft:copper_ore":3,"minecraft:lapis_ore":1,"minecraft:polished_blackstone_brick_stairs":3,"minecraft:diorite":50,"refurbished_furniture:workbench":1,"minecraft:birch_planks":43,"minecraft:cobblestone_wall":4,"minecraft:sweet_berry_bush":2,"minecraft:birch_leaves":1,"refurbished_furniture:white_sofa":1,"minecraft:coal_ore":49,"minecraft:gravel":2},"minecraft:used":{"minecraft:writable_book":1,"minecraft:spruce_slab":21,"farmersdelight:cabbage_seeds":153,"minecraft:diamond_hoe":400,"minecraft:ladder":1,"refurbished_furniture:yellow_lamp":1,"minecraft:chest":7,"minecraft:shield":57,"minecraft:stone":64,"minecraft:iron_chestplate":1,"refurbished_furniture:doorbell":2,"refurbished_furniture:knife":6,"refurbished_furniture:cheese_toastie":4,"purecoppertools:oxidized_copper_leggings":2,"minecraft:carrot":72,"minecraft:deepslate_tile_slab":12,"minecraft:obsidian":1,"minecraft:music_disc_pigstep":5,"minecraft:panda_spawn_egg":40,"purecoppertools:oxidized_copper_chestplate":2,"minecraft:grass_block":34,"minecraft:lantern":2,"music:millpp":1,"minecraft:birch_sapling":6,"refurbished_furniture:light_microwave":2,"farmersdelight:rotten_tomato":5,"minecraft:iron_helmet":1,"minecraft:light_blue_bed":3,"refurbished_furniture:dark_lightswitch":3,"minecraft:netherite_boots":2,"minecraft:birch_trapdoor":5,"refurbished_furniture:oak_crate":19,"farmersdelight:cutting_board":2,"minecraft:written_book":1,"minecraft:sweet_berries":2,"minecraft:furnace":1,"minecraft:beetroot_seeds":49,"minecraft:egg":4,"minecraft:potato":96,"refurbished_furniture:oak_table":11,"cbb:david":6,"minecraft:stone_pickaxe":27,"minecraft:oak_planks":3,"minecraft:blackstone":11,"minecraft:wooden_pickaxe":18,"minecraft:redstone_block":42,"minecraft:sugar_cane":6,"minecraft:netherite_leggings":2,"minecraft:loom":1,"minecraft:blast_furnace":1,"minecraft:netherite_helmet":2,"refurbished_furniture:computer":3,"minecraft:deepslate_tiles":7,"waystones:red_sharestone":1,"refurbished_furniture:birch_light_ceiling_fan":6,"purecoppertools:oxidized_copper_boots":2,"minecraft:crying_obsidian":15,"minecraft:birch_slab":82,"refurbished_furniture:birch_table":4,"farmersdelight:ham":1,"waystones:light_gray_sharestone":4,"purecoppertools:oxidized_copper_helmet":2,"minecraft:diamond_sword":58,"refurbished_furniture:black_trampoline":1,"minecraft:grindstone":1,"minecraft:smithing_table":1,"minecraft:birch_log":1,"refurbished_furniture:oak_storage_cabinet":4,"minecraft:oak_fence":4,"minecraft:netherite_sword":16,"minecraft:stone_sword":16,"minecraft:enchanting_table":1,"minecraft:music_disc_otherside":2,"minecraft:flint_and_steel":1,"minecraft:stone_shovel":125,"minecraft:spruce_planks":28,"refurbished_furniture:light_fridge":2,"refurbished_furniture:oak_storage_jar":2,"coffee_delight:coffee_berries":7,"refurbished_furniture:dark_ceiling_light":50,"minecraft:netherrack":11,"minecraft:torch":5,"refurbished_furniture:black_kitchen_drawer":1,"minecraft:dirt":4,"minecraft:warped_wart_block":8,"minecraft:anvil":1,"elevatorid:elevator_black":4,"minecraft:cobblestone_wall":5,"refurbished_furniture:television":7,"minecraft:spruce_fence":17,"minecraft:birch_door":6,"minecraft:iron_hoe":202,"minecraft:wooden_axe":14,"refurbished_furniture:birch_chair":4,"refurbished_furniture:light_toaster":3,"refurbished_furniture:birch_dark_ceiling_fan":2,"minecraft:iron_boots":1,"minecraft:barrel":5,"elevatorid:elevator_red":3,"minecraft:melon_seeds":24,"minecraft:bamboo":2,"minecraft:blaze_spawn_egg":1,"refurbished_furniture:light_lightswitch":5,"minecraft:deepslate_tile_stairs":49,"minecraft:netherite_pickaxe":1,"waystones:white_sharestone":1,"farmersdelight:tomato_seeds":1,"minecraft:iron_leggings":1,"minecraft:wheat_seeds":188,"farmersdelight:iron_knife":5,"minecraft:birch_planks":882,"minecraft:netherite_chestplate":2,"minecraft:cartography_table":1,"minecraft:fletching_table":1,"minecraft:stonecutter":1,"minecraft:polished_blackstone_bricks":5,"farmersdelight:onion":74,"minecraft:tnt":608,"minecraft:crafting_table":4,"minecraft:red_bed":1,"refurbished_furniture:red_grill":1,"refurbished_furniture:oak_cutting_board":3,"minecraft:phantom_spawn_egg":19,"refurbished_furniture:oak_light_ceiling_fan":3,"minecraft:smoker":1,"refurbished_furniture:dark_electricity_generator":1,"minecraft:diamond_pickaxe":444,"minecraft:diamond_shovel":3,"refurbished_furniture:light_blue_lamp":4,"refurbished_furniture:light_ceiling_light":16,"refurbished_furniture:light_electricity_generator":1,"elevatorid:elevator_light_blue":3,"minecraft:stone_axe":52,"refurbished_furniture:workbench":1,"minecraft:cobblestone":4,"minecraft:potion":3,"minecraft:porkchop":1,"minecraft:splash_potion":67,"minecraft:jukebox":3,"minecraft:birch_stairs":42},"minecraft:picked_up":{"refurbished_furniture:oak_storage_cabinet":1,"refurbished_furniture:light_microwave":1,"minecraft:birch_door":2,"minecraft:wheat":187,"refurbished_furniture:dough":2,"refurbished_furniture:cheese_toastie":1,"music:millpp":3,"farmersdelight:rice_panicle":88,"refurbished_furniture:vegetable_pizza_slice":1,"minecraft:potion":2,"minecraft:gilded_blackstone":5,"refurbished_furniture:computer":2,"minecraft:polished_blackstone_brick_stairs":3,"minecraft:raw_copper":11,"minecraft:netherite_ingot":3,"minecraft:beetroot":46,"farmersdelight:fried_rice":1,"farmersdelight:cabbage":145,"minecraft:written_book":1,"farmersdelight:pasta_with_meatballs":1,"minecraft:melon_slice":117,"farmersdelight:ratatouille":1,"farmersdelight:cabbage_seeds":428,"minecraft:stick":15,"minecraft:jukebox":1,"farmersdelight:rotten_tomato":11,"minecraft:birch_trapdoor":1,"minecraft:torch":2,"minecraft:porkchop":33,"minecraft:music_disc_pigstep":5,"minecraft:diorite":50,"refurbished_furniture:doorbell":2,"farmersdelight:melon_popsicle":1,"refurbished_furniture:cooked_meatlovers_pizza":1,"minecraft:stone_sword":2,"refurbished_furniture:light_toaster":1,"refurbished_furniture:light_lightswitch":5,"farmersdelight:onion":281,"refurbished_furniture:television":3,"farmersdelight:melon_juice":1,"minecraft:cobblestone":250,"minecraft:birch_log":60,"minecraft:enchanting_table":1,"farmersdelight:mixed_salad":1,"refurbished_furniture:glow_berry_jam":1,"refurbished_furniture:oak_light_ceiling_fan":2,"minecraft:feather":2,"minecraft:cooked_beef":22,"minecraft:birch_slab":3,"witherstormmod:amulet":1,"minecraft:potato":151,"refurbished_furniture:red_cooler":1,"minecraft:flint":1,"minecraft:dirt":173,"minecraft:lapis_lazuli":4,"farmersdelight:chicken_sandwich":1,"farmersdelight:tomato":260,"coffee_delight:cup_black_coffee":1,"minecraft:bone":10,"farmersdelight:iron_knife":2,"minecraft:wheat_seeds":522,"farmersdelight:sweet_berry_cookie":1,"refurbished_furniture:wheat_flour":1,"farmersdelight:egg_sandwich":1,"minecraft:bamboo":33,"refurbished_furniture:sea_salt":1,"refurbished_furniture:oak_cutting_board":5,"minecraft:oak_planks":6,"farmersdelight:ham":2,"minecraft:iron_hoe":1,"farmersdelight:glow_berry_custard":1,"refurbished_furniture:glow_berry_jam_toast":1,"minecraft:writable_book":1,"minecraft:cracked_polished_blackstone_bricks":2,"cbb:david":8,"minecraft:netherrack":90,"minecraft:crimson_roots":1,"minecraft:crafting_table":2,"farmersdelight:sweet_berry_cheesecake_slice":1,"minecraft:nether_wart":3,"minecraft:chicken":1,"minecraft:ladder":1,"refurbished_furniture:light_fridge":1,"refurbished_furniture:white_sofa":1,"minecraft:wooden_pickaxe":2,"minecraft:gold_block":13,"cbb:boner":1,"cbb:spectral_dust":2,"minecraft:cornflower":9,"minecraft:red_bed":1,"minecraft:blackstone":32,"minecraft:music_disc_otherside":2,"minecraft:beef":2,"refurbished_furniture:light_electricity_generator":1,"minecraft:sugar_cane":126,"minecraft:chest":3,"minecraft:birch_sapling":23,"minecraft:diamond_hoe":2,"minecraft:egg":4,"minecraft:raw_iron":18,"refurbished_furniture:cheese":1,"minecraft:copper_ingot":38,"minecraft:polished_blackstone_bricks":9,"farmersdelight:tomato_seeds":1,"minecraft:carrot":273,"refurbished_furniture:red_grill":1,"minecraft:beetroot_seeds":136,"refurbished_furniture:meatlovers_pizza_slice":1,"farmersdelight:hamburger":1,"refurbished_furniture:oak_storage_jar":3,"minecraft:mutton":3,"minecraft:white_wool":2,"minecraft:oxeye_daisy":1,"minecraft:basalt":7,"minecraft:salmon":2,"minecraft:leather":1,"minecraft:birch_planks":43,"refurbished_furniture:yellow_lamp":1,"minecraft:cobblestone_wall":5,"minecraft:wooden_hoe":26,"coffee_delight:coffee_berries":157,"minecraft:glass_bottle":1,"refurbished_furniture:dark_lightswitch":1,"minecraft:book":3,"refurbished_furniture:sweet_berry_jam_toast":2,"minecraft:sweet_berries":58,"minecraft:dandelion":6,"minecraft:gravel":1,"refurbished_furniture:light_ceiling_light":3,"refurbished_furniture:workbench":3,"minecraft:melon_seeds":8,"minecraft:coal":105}},"DataVersion":3465}